do_utils/__init__.py
do_utils/do_cache.py
do_utils/do_time.py
do_utils/do_xlsx.py
do_utils-0.0.4.2.dist-info/LICENSE
do_utils-0.0.4.2.dist-info/METADATA
do_utils-0.0.4.2.dist-info/WHEEL
do_utils-0.0.4.2.dist-info/top_level.txt
do_utils-0.0.4.2.dist-info/zip-safe
do_utils-0.0.4.2.dist-info/RECORD
