Metadata-Version: 2.1
Name: do-utils
Version: 0.0.4.2
Summary: Utils for tornado api cache, function timer.
Home-page: https://github.com/hustjiangtao/do_utils
Author: jiangtao
Author-email: jiangtao.work@gmail.com
License: http://www.apache.org/licenses/LICENSE-2.0
Keywords: utils,do_utils,cache,time,do_cache,do_time
Classifier: Programming Language :: Python :: 2.7
Classifier: License :: OSI Approved :: Apache Software License
Classifier: Operating System :: OS Independent
Classifier: Intended Audience :: Developers
Requires-Python: >=2.7.14
License-File: LICENSE
Requires-Dist: ujson ==1.35
Requires-Dist: xlwt <=2.0.0,>=1.3.0
Requires-Dist: openpyxl >=2.6.2
